{"is_source_file": true, "format": "C++ header", "description": "This file declares the SystemDelegate class, which provides an interface for interacting with the org.rdk.System component. It includes methods to retrieve system information such as friendly name, timezone, platform configuration, device ID, and system settings. The class utilizes helper utilities for JSON serialization and link acquisition to communicate with the underlying system components.", "external_files": ["DelegateUtils.h"], "external_methods": ["DelegateUtils::AcquireLink", "DelegateUtils::SerializeToJsonString", "Core::ERROR_UNAVAILABLE", "Core::ERROR_NONE", "Core::ERROR_UNAVAILABLE", "Core::ERROR_GENERAL", "Core::ERROR_NONE", "Core::hresult", "JsonObject"], "published": ["GetFriendlyName", "GetTimeZone", "GetSystemPlatformConfiguration", "GetDeviceId", "BuildSettings"], "classes": [{"name": "SystemDelegate", "description": "A class to interface with the org.rdk.System component for retrieving system information and configuration."}], "methods": [{"name": "uint32_t GetFriendlyName(std::string & friendlyNameJson)", "description": "Calls org.rdk.System.getFriendlyName and returns a JSON string containing the friendly name.", "scope": "SystemDelegate", "scopeKind": "class"}, {"name": "Core::hresult GetTimeZone(std::string & tzJson)", "description": "Retrieves the system's timezone using org.rdk.System.getTimeZoneDST and returns it as a JSON string.", "scope": "SystemDelegate", "scopeKind": "class"}, {"name": "uint32_t GetSystemPlatformConfiguration(std::string & platformConfigJson)", "description": "Calls org.rdk.System.getPlatformConfiguration and extracts system details into a JSON string.", "scope": "SystemDelegate", "scopeKind": "class"}, {"name": "uint32_t GetDeviceId(std::string & deviceIdJson)", "description": "Uses platform configuration to build a JSON object with the device ID.", "scope": "SystemDelegate", "scopeKind": "class"}, {"name": "Core::hresult BuildSettings(const std::vector<std::string> & keys,WPEFramework::Core::JSON::VariantContainer & out) const", "description": "Aggregates specified system settings, such as friendly name and power status, into a JSON object.", "scope": "SystemDelegate", "scopeKind": "class"}, {"name": "SystemDelegate(PluginHost::IShell * shell)", "scope": "SystemDelegate", "scopeKind": "class", "description": "unavailable"}], "calls": ["DelegateUtils::AcquireLink", "link->Invoke", "DelegateUtils::SerializeToJsonString", "response.HasLabel", "response[label]", "Core::ERROR_NONE", "Core::ERROR_UNAVAILABLE", "Core::ERROR_GENERAL"], "search-terms": ["SystemDelegate", "org.rdk.System", "getFriendlyName", "getTimeZoneDST", "getPlatformConfiguration", "device_id", "BuildSettings", "DelegateUtils", "JsonObject", "PluginHost::IShell"], "state": 2, "file_id": 1137, "knowledge_revision": 11394, "git_revision": "2cc9c66935ba4fb0f3bb8bf9c0b1056dde5ea4b4", "revision_history": [{"3764": "2cc9c66935ba4fb0f3bb8bf9c0b1056dde5ea4b4"}, {"11394": "2cc9c66935ba4fb0f3bb8bf9c0b1056dde5ea4b4"}], "ctags": [{"_type": "tag", "name": "BuildSettings", "path": "/home/kavia/workspace/code-generation/app-gateway2/app-gateway/Badger/Delegate/SystemDelegate.h", "pattern": "/^    Core::hresult BuildSettings(const std::vector<std::string>& keys,$/", "language": "C++", "typeref": "typename:Core::hresult", "kind": "function", "signature": "(const std::vector<std::string> & keys,WPEFramework::Core::JSON::VariantContainer & out) const", "scope": "SystemDelegate", "scopeKind": "class"}, {"_type": "tag", "name": "GetDeviceId", "path": "/home/kavia/workspace/code-generation/app-gateway2/app-gateway/Badger/Delegate/SystemDelegate.h", "pattern": "/^    uint32_t GetDeviceId(std::string& deviceIdJson) {$/", "language": "C++", "typeref": "typename:uint32_t", "kind": "function", "signature": "(std::string & deviceIdJson)", "scope": "SystemDelegate", "scopeKind": "class"}, {"_type": "tag", "name": "GetFriendlyName", "path": "/home/kavia/workspace/code-generation/app-gateway2/app-gateway/Badger/Delegate/SystemDelegate.h", "pattern": "/^    uint32_t GetFriendlyName(std::string& friendlyNameJson) {$/", "language": "C++", "typeref": "typename:uint32_t", "kind": "function", "signature": "(std::string & friendlyNameJson)", "scope": "SystemDelegate", "scopeKind": "class"}, {"_type": "tag", "name": "GetSystemPlatformConfiguration", "path": "/home/kavia/workspace/code-generation/app-gateway2/app-gateway/Badger/Delegate/SystemDelegate.h", "pattern": "/^    uint32_t GetSystemPlatformConfiguration(std::string& platformConfigJson) {$/", "language": "C++", "typeref": "typename:uint32_t", "kind": "function", "signature": "(std::string & platformConfigJson)", "scope": "SystemDelegate", "scopeKind": "class"}, {"_type": "tag", "name": "GetTimeZone", "path": "/home/kavia/workspace/code-generation/app-gateway2/app-gateway/Badger/Delegate/SystemDelegate.h", "pattern": "/^    Core::hresult GetTimeZone(std::string& tzJson) {$/", "language": "C++", "typeref": "typename:Core::hresult", "kind": "function", "signature": "(std::string & tzJson)", "scope": "SystemDelegate", "scopeKind": "class"}, {"_type": "tag", "name": "SYSTEM_CALLSIGN", "path": "/home/kavia/workspace/code-generation/app-gateway2/app-gateway/Badger/Delegate/SystemDelegate.h", "pattern": "/^#define SYSTEM_CALLSIGN /", "language": "C++", "kind": "macro"}, {"_type": "tag", "name": "SystemDelegate", "path": "/home/kavia/workspace/code-generation/app-gateway2/app-gateway/Badger/Delegate/SystemDelegate.h", "pattern": "/^    SystemDelegate(PluginHost::IShell* shell) : _shell(shell) {}$/", "language": "C++", "kind": "function", "signature": "(PluginHost::IShell * shell)", "scope": "SystemDelegate", "scopeKind": "class"}, {"_type": "tag", "name": "SystemDelegate", "path": "/home/kavia/workspace/code-generation/app-gateway2/app-gateway/Badger/Delegate/SystemDelegate.h", "pattern": "/^class SystemDelegate {$/", "language": "C++", "kind": "class"}, {"_type": "tag", "name": "_shell", "path": "/home/kavia/workspace/code-generation/app-gateway2/app-gateway/Badger/Delegate/SystemDelegate.h", "pattern": "/^    PluginHost::IShell* _shell;$/", "language": "C++", "typeref": "typename:PluginHost::IShell *", "kind": "member", "scope": "SystemDelegate", "scopeKind": "class"}, {"_type": "tag", "name": "mAdminLock", "path": "/home/kavia/workspace/code-generation/app-gateway2/app-gateway/Badger/Delegate/SystemDelegate.h", "pattern": "/^    mutable Core::CriticalSection mAdminLock;$/", "language": "C++", "typeref": "typename:Core::CriticalSection", "kind": "member", "scope": "SystemDelegate", "scopeKind": "class"}], "hash": "3f3863faaf03c2a13d20aa8c8b7cdefa", "format-version": 4, "code-base-name": "app-gateway2", "filename": "app-gateway/Badger/Delegate/SystemDelegate.h", "fields": [{"name": "PluginHost::IShell * _shell", "scope": "SystemDelegate", "scopeKind": "class", "description": "unavailable"}, {"name": "Core::CriticalSection mAdminLock", "scope": "SystemDelegate", "scopeKind": "class", "description": "unavailable"}]}