{"is_source_file": true, "format": "C++ header file", "description": "This file defines a helper class JOttServices for registering and unregistering JSON-RPC methods (ott.getDistributorToken and ott.getAuthToken) related to IOttServices in the WPEFramework. It provides function wrappers for external modules to interact with OttServices via JSON-RPC.", "external_files": ["<plugins/JSONRPC.h>", "<core/JSON.h>", "<string>"], "external_methods": ["PluginHost::JSONRPC::Register", "PluginHost::JSONRPC::Unregister", "Core::JSON::VariantContainer::FromString", "Core::JSON::String::operator="], "published": ["WPEFramework::Exchange::JOttServices"], "classes": [{"name": "JOttServices", "description": "Helper struct for registering/deregistering JSONRPC methods for OTT services."}], "methods": [{"name": "void Register(PluginHost::JSONRPC & parent,IOttServices * api)", "description": "Registers OTT related JSONRPC methods for a given IOttServices implementation.", "scope": "WPEFramework::Exchange::JOttServices", "scopeKind": "struct"}, {"name": "void Unregister(PluginHost::JSONRPC & parent)", "description": "Unregisters OTT related JSONRPC methods.", "scope": "WPEFramework::Exchange::JOttServices", "scopeKind": "struct"}, {"name": "uint32_t __anon354345af0102(const Core::JSONRPC::Context& , const string& , const string& parameters, string& response)", "scope": "WPEFramework::Exchange::JOttServices::Register", "scopeKind": "function", "description": "unavailable"}, {"name": "uint32_t __anon354345af0202(const Core::JSONRPC::Context& , const string& , const string& parameters, string& response)", "scope": "WPEFramework::Exchange::JOttServices::Register", "scopeKind": "function", "description": "unavailable"}], "calls": ["api->GetDistributorToken", "api->GetAuthToken", "parent.Register", "parent.Unregister"], "search-terms": ["JOttServices", "JSONRPC", "ott.getDistributorToken", "ott.getAuthToken", "IOttServices", "JSONRPC registration"], "state": 2, "file_id": 127, "knowledge_revision": 16357, "git_revision": "2acc6b1f2164c745a826a53df19f520f5fc28d21", "revision_history": [{"407": "758c7387764e198c832ddc6c3181fe4b0fbf5555"}, {"16328": "0f87a35b32215bc8547fb583d6c84bd51f603f69"}, {"16345": "b6496a978f0d461a81579869494de03baf1df52c"}, {"16357": "2acc6b1f2164c745a826a53df19f520f5fc28d21"}], "ctags": [{"_type": "tag", "name": "Exchange", "path": "/home/kavia/workspace/code-generation/app-gateway2/app-gateway/interfaces/json/JOttServices.h", "pattern": "/^namespace Exchange {$/", "language": "C++", "kind": "namespace", "scope": "WPEFramework", "scopeKind": "namespace"}, {"_type": "tag", "name": "JOttServices", "path": "/home/kavia/workspace/code-generation/app-gateway2/app-gateway/interfaces/json/JOttServices.h", "pattern": "/^    struct JOttServices {$/", "language": "C++", "kind": "struct", "scope": "WPEFramework::Exchange", "scopeKind": "namespace"}, {"_type": "tag", "name": "PluginHost", "path": "/home/kavia/workspace/code-generation/app-gateway2/app-gateway/interfaces/json/JOttServices.h", "pattern": "/^namespace PluginHost {$/", "language": "C++", "kind": "namespace", "scope": "WPEFramework", "scopeKind": "namespace"}, {"_type": "tag", "name": "Register", "path": "/home/kavia/workspace/code-generation/app-gateway2/app-gateway/interfaces/json/JOttServices.h", "pattern": "/^        static void Register(PluginHost::JSONRPC& parent, IOttServices* api) {$/", "language": "C++", "typeref": "typename:void", "kind": "function", "signature": "(PluginHost::JSONRPC & parent,IOttServices * api)", "scope": "WPEFramework::Exchange::JOttServices", "scopeKind": "struct"}, {"_type": "tag", "name": "Unregister", "path": "/home/kavia/workspace/code-generation/app-gateway2/app-gateway/interfaces/json/JOttServices.h", "pattern": "/^        static void Unregister(PluginHost::JSONRPC& parent) {$/", "language": "C++", "typeref": "typename:void", "kind": "function", "signature": "(PluginHost::JSONRPC & parent)", "scope": "WPEFramework::Exchange::JOttServices", "scopeKind": "struct"}, {"_type": "tag", "name": "WPEFramework", "path": "/home/kavia/workspace/code-generation/app-gateway2/app-gateway/interfaces/json/JOttServices.h", "pattern": "/^namespace WPEFramework {$/", "language": "C++", "kind": "namespace"}, {"_type": "tag", "name": "__anon354345af0102", "path": "/home/kavia/workspace/code-generation/app-gateway2/app-gateway/interfaces/json/JOttServices.h", "pattern": "/^                [api](const Core::JSONRPC::Context& \\/*ctx*\\/, const string& \\/*method*\\/, const/", "file": true, "language": "C++", "typeref": "typename:uint32_t", "kind": "function", "signature": "(const Core::JSONRPC::Context& , const string& , const string& parameters, string& response) ", "scope": "WPEFramework::Exchange::JOttServices::Register", "scopeKind": "function"}, {"_type": "tag", "name": "__anon354345af0202", "path": "/home/kavia/workspace/code-generation/app-gateway2/app-gateway/interfaces/json/JOttServices.h", "pattern": "/^                [api](const Core::JSONRPC::Context& \\/*ctx*\\/, const string& \\/*method*\\/, const/", "file": true, "language": "C++", "typeref": "typename:uint32_t", "kind": "function", "signature": "(const Core::JSONRPC::Context& , const string& , const string& parameters, string& response) ", "scope": "WPEFramework::Exchange::JOttServices::Register", "scopeKind": "function"}], "hash": "6548b3eb39c8b7994d846704402adbc6", "format-version": 4, "code-base-name": "app-gateway2", "filename": "app-gateway/interfaces/json/JOttServices.h"}