{"is_source_file": false, "format": "", "description": "", "external_files": [], "external_methods": [], "published": [], "classes": [], "methods": [], "calls": [], "search-terms": [], "state": 2, "file_id": 9020, "knowledge_revision": 18146, "git_revision": "75be2917f370a78d398cf01eea20b67eb940d189", "hash": "671c33842dc319d26873d1584fe5181b", "format-version": 4, "code-base-name": "app-gateway2", "filename": "build/plugin_appgateway_20260105_063001_cxx11/CMakeFiles/3.28.3/CMakeCCompiler.cmake", "revision_history": [{"18146": "75be2917f370a78d398cf01eea20b67eb940d189"}]}