{"is_source_file": true, "format": "C++ header file", "description": "This file defines the interface for plugins within the WPEFramework, including plugin management, notifications, WebSocket, security, and communication interfaces. It contains multiple class and struct definitions with virtual functions, used to interact with plugin lifecycle events, communication channels, and security checks.", "external_files": ["com/ICOM.h", "IShell.h"], "external_methods": ["Core::IUnknown", "Core::JSON::IElement", "Core::ProxyType", "Web::Request", "Web::Response", "Core::hresult", "Web::Request&", "Web::Response"], "published": ["WPEFramework::PluginHost::IPlugin", "WPEFramework::PluginHost::IPluginExtended", "WPEFramework::PluginHost::ICompositPlugin", "WPEFramework::PluginHost::IWeb", "WPEFramework::PluginHost::IWebSocket", "WPEFramework::PluginHost::ITextSocket", "WPEFramework::PluginHost::IChannel", "WPEFramework::PluginHost::ISecurity", "WPEFramework::PluginHost::IAuthenticate"], "classes": [{"name": "WPEFramework::PluginHost::IPlugin", "description": "Interface for plugins, managing initialization, deinitialization, and information retrieval."}, {"name": "WPEFramework::PluginHost::INotification", "description": "Notification interface for plugin state changes (activation, deactivation, unavailability)."}, {"name": "WPEFramework::PluginHost::ILifeTime", "description": "Interface for managing plugin lifecycle events (initialization and deinitialization)."}, {"name": "WPEFramework::PluginHost::IPluginExtended", "description": "Extended plugin interface for communication channel attachment and detachment."}, {"name": "WPEFramework::PluginHost::ICompositPlugin", "description": "Interface for composite plugins, managing registration of notifications."}, {"name": "WPEFramework::PluginHost::ICompositPlugin::INotification", "description": "Notification interface for composite plugin events."}, {"name": "WPEFramework::PluginHost::IWeb", "description": "Interface for handling incoming web requests and processing them."}, {"name": "WPEFramework::PluginHost::IWebSocket", "description": "Interface for websocket communication, handling inbound messages."}, {"name": "WPEFramework::PluginHost::ITextSocket", "description": "Interface for text socket communication, handling textual inbound messages."}, {"name": "WPEFramework::PluginHost::IChannel", "description": "Interface for raw data channel communication."}, {"name": "WPEFramework::PluginHost::ISecurity", "description": "Interface for security checks on requests, websockets, and URLs, plus token management."}, {"name": "WPEFramework::PluginHost::IAuthenticate", "description": "Interface for creating tokens and obtaining security officers based on tokens."}], "methods": [{"name": "Initialize", "description": "Performs first-time plugin initialization with provided shell."}, {"name": "Deinitialize", "description": "Performs cleanup and deactivation steps for the plugin."}, {"name": "Information", "description": "Returns plugin-specific metadata as a JSON string."}, {"name": "Attach", "description": "Attach a communication channel to the plugin."}, {"name": "Detach", "description": "Detach a communication channel from the plugin."}, {"name": "Register", "description": "Register a notification for the composite plugin."}, {"name": "Unregister", "description": "Unregister a notification for the composite plugin."}, {"name": "Inbound (Web)", "description": "Handle an inbound web request."}, {"name": "Process", "description": "Process a web request and produce a response."}, {"name": "Inbound (WebSocket)", "description": "Inbound message handling for WebSocket."}, {"name": "Inbound (TextSocket)", "description": "Handle inbound text messages."}, {"name": "Inbound (Channel)", "description": "Handle inbound raw data on a channel."}, {"name": "Outbound", "description": "Send data out through the channel."}, {"name": "Allowed (path)", "description": "Check if websocket upgrade is permitted for the provided path."}, {"name": "Allowed (Request)", "description": "Check if a request is permitted before processing."}, {"name": "Allowed (message)", "description": "Check if a JSONRPC message is permitted before processing."}, {"name": "Token", "description": "Retrieve the security token payload."}, {"name": "CreateToken", "description": "Generate a security token from a buffer."}, {"name": "Officer", "description": "Obtain security officer object based on a token."}], "calls": ["Core::IUnknown", "Core::JSON::IElement", "Core::ProxyType<Web::Response>", "Core::ProxyType<Core::JSON::IElement>", "Core::hresult", "Web::Request", "Web::Response", "Core::JSONRPC::Message"], "search-terms": ["IPlugin", "WebSocket", "Security", "Notification", "Plugin lifecycle", "Web request handling", "Channel communication", "Token management", "COM interface"], "state": 2, "file_id": 2247, "knowledge_revision": 4834, "git_revision": "", "ctags": [{"_type": "tag", "name": "IAuthenticate", "path": "/home/kavia/workspace/code-generation/app-gateway2/dependencies/Thunder/Source/plugins/IPlugin.h", "pattern": "/^    struct IAuthenticate : virtual public Core::IUnknown {$/", "language": "C++", "kind": "struct", "scope": "WPEFramework::PluginHost", "scopeKind": "namespace"}, {"_type": "tag", "name": "IChannel", "path": "/home/kavia/workspace/code-generation/app-gateway2/dependencies/Thunder/Source/plugins/IPlugin.h", "pattern": "/^    struct IChannel : virtual public Core::IUnknown {$/", "language": "C++", "kind": "struct", "scope": "WPEFramework::PluginHost", "scopeKind": "namespace"}, {"_type": "tag", "name": "ICompositPlugin", "path": "/home/kavia/workspace/code-generation/app-gateway2/dependencies/Thunder/Source/plugins/IPlugin.h", "pattern": "/^    struct EXTERNAL ICompositPlugin : public virtual Core::IUnknown {$/", "language": "C++", "kind": "struct", "scope": "WPEFramework::PluginHost", "scopeKind": "namespace"}, {"_type": "tag", "name": "ID", "path": "/home/kavia/workspace/code-generation/app-gateway2/dependencies/Thunder/Source/plugins/IPlugin.h", "pattern": "/^            enum { ID = RPC::ID_COMPOSIT_PLUGIN_NOTIFICATION };$/", "language": "C++", "kind": "enumerator", "scope": "WPEFramework::PluginHost::ICompositPlugin::INotification::__anone27382070603", "scopeKind": "enum"}, {"_type": "tag", "name": "ID", "path": "/home/kavia/workspace/code-generation/app-gateway2/dependencies/Thunder/Source/plugins/IPlugin.h", "pattern": "/^            enum { ID = RPC::ID_PLUGIN_LIFETIME };$/", "language": "C++", "kind": "enumerator", "scope": "WPEFramework::PluginHost::IPlugin::ILifeTime::__anone27382070303", "scopeKind": "enum"}, {"_type": "tag", "name": "ID", "path": "/home/kavia/workspace/code-generation/app-gateway2/dependencies/Thunder/Source/plugins/IPlugin.h", "pattern": "/^            enum { ID = RPC::ID_PLUGIN_NOTIFICATION };$/", "language": "C++", "kind": "enumerator", "scope": "WPEFramework::PluginHost::IPlugin::INotification::__anone27382070203", "scopeKind": "enum"}, {"_type": "tag", "name": "ID", "path": "/home/kavia/workspace/code-generation/app-gateway2/dependencies/Thunder/Source/plugins/IPlugin.h", "pattern": "/^        enum { ID = RPC::ID_AUTHENTICATE };$/", "language": "C++", "kind": "enumerator", "scope": "WPEFramework::PluginHost::IAuthenticate::__anone27382070c03", "scopeKind": "enum"}, {"_type": "tag", "name": "ID", "path": "/home/kavia/workspace/code-generation/app-gateway2/dependencies/Thunder/Source/plugins/IPlugin.h", "pattern": "/^        enum { ID = RPC::ID_CHANNEL };$/", "language": "C++", "kind": "enumerator", "scope": "WPEFramework::PluginHost::IChannel::__anone27382070a03", "scopeKind": "enum"}, {"_type": "tag", "name": "ID", "path": "/home/kavia/workspace/code-generation/app-gateway2/dependencies/Thunder/Source/plugins/IPlugin.h", "pattern": "/^        enum { ID = RPC::ID_COMPOSIT_PLUGIN };$/", "language": "C++", "kind": "enumerator", "scope": "WPEFramework::PluginHost::ICompositPlugin::__anone27382070503", "scopeKind": "enum"}, {"_type": "tag", "name": "ID", "path": "/home/kavia/workspace/code-generation/app-gateway2/dependencies/Thunder/Source/plugins/IPlugin.h", "pattern": "/^        enum { ID = RPC::ID_PLUGIN };$/", "language": "C++", "kind": "enumerator", "scope": "WPEFramework::PluginHost::IPlugin::__anone27382070103", "scopeKind": "enum"}, {"_type": "tag", "name": "ID", "path": "/home/kavia/workspace/code-generation/app-gateway2/dependencies/Thunder/Source/plugins/IPlugin.h", "pattern": "/^        enum { ID = RPC::ID_PLUGINEXTENDED };$/", "language": "C++", "kind": "enumerator", "scope": "WPEFramework::PluginHost::IPluginExtended::__anone27382070403", "scopeKind": "enum"}, {"_type": "tag", "name": "ID", "path": "/home/kavia/workspace/code-generation/app-gateway2/dependencies/Thunder/Source/plugins/IPlugin.h", "pattern": "/^        enum { ID = RPC::ID_SECURITY };$/", "language": "C++", "kind": "enumerator", "scope": "WPEFramework::PluginHost::ISecurity::__anone27382070b03", "scopeKind": "enum"}, {"_type": "tag", "name": "ID", "path": "/home/kavia/workspace/code-generation/app-gateway2/dependencies/Thunder/Source/plugins/IPlugin.h", "pattern": "/^        enum { ID = RPC::ID_TEXTSOCKET };$/", "language": "C++", "kind": "enumerator", "scope": "WPEFramework::PluginHost::ITextSocket::__anone27382070903", "scopeKind": "enum"}, {"_type": "tag", "name": "ID", "path": "/home/kavia/workspace/code-generation/app-gateway2/dependencies/Thunder/Source/plugins/IPlugin.h", "pattern": "/^        enum { ID = RPC::ID_WEB };$/", "language": "C++", "kind": "enumerator", "scope": "WPEFramework::PluginHost::IWeb::__anone27382070703", "scopeKind": "enum"}, {"_type": "tag", "name": "ID", "path": "/home/kavia/workspace/code-generation/app-gateway2/dependencies/Thunder/Source/plugins/IPlugin.h", "pattern": "/^        enum { ID = RPC::ID_WEBSOCKET };$/", "language": "C++", "kind": "enumerator", "scope": "WPEFramework::PluginHost::IWebSocket::__anone27382070803", "scopeKind": "enum"}, {"_type": "tag", "name": "ILifeTime", "path": "/home/kavia/workspace/code-generation/app-gateway2/dependencies/Thunder/Source/plugins/IPlugin.h", "pattern": "/^        struct ILifeTime : virtual public Core::IUnknown {$/", "language": "C++", "kind": "struct", "scope": "WPEFramework::PluginHost::IPlugin", "scopeKind": "struct"}, {"_type": "tag", "name": "INotification", "path": "/home/kavia/workspace/code-generation/app-gateway2/dependencies/Thunder/Source/plugins/IPlugin.h", "pattern": "/^        struct EXTERNAL INotification : public virtual Core::IUnknown {$/", "language": "C++", "kind": "struct", "scope": "WPEFramework::PluginHost::ICompositPlugin", "scopeKind": "struct"}, {"_type": "tag", "name": "INotification", "path": "/home/kavia/workspace/code-generation/app-gateway2/dependencies/Thunder/Source/plugins/IPlugin.h", "pattern": "/^        struct INotification : virtual public Core::IUnknown {$/", "language": "C++", "kind": "struct", "scope": "WPEFramework::PluginHost::IPlugin", "scopeKind": "struct"}, {"_type": "tag", "name": "IPlugin", "path": "/home/kavia/workspace/code-generation/app-gateway2/dependencies/Thunder/Source/plugins/IPlugin.h", "pattern": "/^    struct EXTERNAL IPlugin : public virtual Core::IUnknown {$/", "language": "C++", "kind": "struct", "scope": "WPEFramework::PluginHost", "scopeKind": "namespace"}, {"_type": "tag", "name": "IPluginExtended", "path": "/home/kavia/workspace/code-generation/app-gateway2/dependencies/Thunder/Source/plugins/IPlugin.h", "pattern": "/^    struct IPluginExtended : public IPlugin {$/", "language": "C++", "kind": "struct", "scope": "WPEFramework::PluginHost", "scopeKind": "namespace"}, {"_type": "tag", "name": "ISecurity", "path": "/home/kavia/workspace/code-generation/app-gateway2/dependencies/Thunder/Source/plugins/IPlugin.h", "pattern": "/^    struct ISecurity : virtual public Core::IUnknown {$/", "language": "C++", "kind": "struct", "scope": "WPEFramework::PluginHost", "scopeKind": "namespace"}, {"_type": "tag", "name": "ITextSocket", "path": "/home/kavia/workspace/code-generation/app-gateway2/dependencies/Thunder/Source/plugins/IPlugin.h", "pattern": "/^    struct ITextSocket : virtual public Core::IUnknown {$/", "language": "C++", "kind": "struct", "scope": "WPEFramework::PluginHost", "scopeKind": "namespace"}, {"_type": "tag", "name": "IWeb", "path": "/home/kavia/workspace/code-generation/app-gateway2/dependencies/Thunder/Source/plugins/IPlugin.h", "pattern": "/^    struct IWeb : virtual public Core::IUnknown {$/", "language": "C++", "kind": "struct", "scope": "WPEFramework::PluginHost", "scopeKind": "namespace"}, {"_type": "tag", "name": "IWebSocket", "path": "/home/kavia/workspace/code-generation/app-gateway2/dependencies/Thunder/Source/plugins/IPlugin.h", "pattern": "/^    struct IWebSocket : virtual public Core::IUnknown {$/", "language": "C++", "kind": "struct", "scope": "WPEFramework::PluginHost", "scopeKind": "namespace"}, {"_type": "tag", "name": "PluginHost", "path": "/home/kavia/workspace/code-generation/app-gateway2/dependencies/Thunder/Source/plugins/IPlugin.h", "pattern": "/^namespace PluginHost {$/", "language": "C++", "kind": "namespace", "scope": "WPEFramework", "scopeKind": "namespace"}, {"_type": "tag", "name": "WPEFramework", "path": "/home/kavia/workspace/code-generation/app-gateway2/dependencies/Thunder/Source/plugins/IPlugin.h", "pattern": "/^namespace WPEFramework {$/", "language": "C++", "kind": "namespace"}, {"_type": "tag", "name": "Web", "path": "/home/kavia/workspace/code-generation/app-gateway2/dependencies/Thunder/Source/plugins/IPlugin.h", "pattern": "/^namespace Web {$/", "language": "C++", "kind": "namespace", "scope": "WPEFramework", "scopeKind": "namespace"}, {"_type": "tag", "name": "__IPLUGIN_H__", "path": "/home/kavia/workspace/code-generation/app-gateway2/dependencies/Thunder/Source/plugins/IPlugin.h", "pattern": "/^#define __IPLUGIN_H__$/", "language": "C++", "kind": "macro"}, {"_type": "tag", "name": "__anone27382070103", "path": "/home/kavia/workspace/code-generation/app-gateway2/dependencies/Thunder/Source/plugins/IPlugin.h", "pattern": "/^        enum { ID = RPC::ID_PLUGIN };$/", "language": "C++", "kind": "enum", "scope": "WPEFramework::PluginHost::IPlugin", "scopeKind": "struct"}, {"_type": "tag", "name": "__anone27382070203", "path": "/home/kavia/workspace/code-generation/app-gateway2/dependencies/Thunder/Source/plugins/IPlugin.h", "pattern": "/^            enum { ID = RPC::ID_PLUGIN_NOTIFICATION };$/", "language": "C++", "kind": "enum", "scope": "WPEFramework::PluginHost::IPlugin::INotification", "scopeKind": "struct"}, {"_type": "tag", "name": "__anone27382070303", "path": "/home/kavia/workspace/code-generation/app-gateway2/dependencies/Thunder/Source/plugins/IPlugin.h", "pattern": "/^            enum { ID = RPC::ID_PLUGIN_LIFETIME };$/", "language": "C++", "kind": "enum", "scope": "WPEFramework::PluginHost::IPlugin::ILifeTime", "scopeKind": "struct"}, {"_type": "tag", "name": "__anone27382070403", "path": "/home/kavia/workspace/code-generation/app-gateway2/dependencies/Thunder/Source/plugins/IPlugin.h", "pattern": "/^        enum { ID = RPC::ID_PLUGINEXTENDED };$/", "language": "C++", "kind": "enum", "scope": "WPEFramework::PluginHost::IPluginExtended", "scopeKind": "struct"}, {"_type": "tag", "name": "__anone27382070503", "path": "/home/kavia/workspace/code-generation/app-gateway2/dependencies/Thunder/Source/plugins/IPlugin.h", "pattern": "/^        enum { ID = RPC::ID_COMPOSIT_PLUGIN };$/", "language": "C++", "kind": "enum", "scope": "WPEFramework::PluginHost::ICompositPlugin", "scopeKind": "struct"}, {"_type": "tag", "name": "__anone27382070603", "path": "/home/kavia/workspace/code-generation/app-gateway2/dependencies/Thunder/Source/plugins/IPlugin.h", "pattern": "/^            enum { ID = RPC::ID_COMPOSIT_PLUGIN_NOTIFICATION };$/", "language": "C++", "kind": "enum", "scope": "WPEFramework::PluginHost::ICompositPlugin::INotification", "scopeKind": "struct"}, {"_type": "tag", "name": "__anone27382070703", "path": "/home/kavia/workspace/code-generation/app-gateway2/dependencies/Thunder/Source/plugins/IPlugin.h", "pattern": "/^        enum { ID = RPC::ID_WEB };$/", "language": "C++", "kind": "enum", "scope": "WPEFramework::PluginHost::IWeb", "scopeKind": "struct"}, {"_type": "tag", "name": "__anone27382070803", "path": "/home/kavia/workspace/code-generation/app-gateway2/dependencies/Thunder/Source/plugins/IPlugin.h", "pattern": "/^        enum { ID = RPC::ID_WEBSOCKET };$/", "language": "C++", "kind": "enum", "scope": "WPEFramework::PluginHost::IWebSocket", "scopeKind": "struct"}, {"_type": "tag", "name": "__anone27382070903", "path": "/home/kavia/workspace/code-generation/app-gateway2/dependencies/Thunder/Source/plugins/IPlugin.h", "pattern": "/^        enum { ID = RPC::ID_TEXTSOCKET };$/", "language": "C++", "kind": "enum", "scope": "WPEFramework::PluginHost::ITextSocket", "scopeKind": "struct"}, {"_type": "tag", "name": "__anone27382070a03", "path": "/home/kavia/workspace/code-generation/app-gateway2/dependencies/Thunder/Source/plugins/IPlugin.h", "pattern": "/^        enum { ID = RPC::ID_CHANNEL };$/", "language": "C++", "kind": "enum", "scope": "WPEFramework::PluginHost::IChannel", "scopeKind": "struct"}, {"_type": "tag", "name": "__anone27382070b03", "path": "/home/kavia/workspace/code-generation/app-gateway2/dependencies/Thunder/Source/plugins/IPlugin.h", "pattern": "/^        enum { ID = RPC::ID_SECURITY };$/", "language": "C++", "kind": "enum", "scope": "WPEFramework::PluginHost::ISecurity", "scopeKind": "struct"}, {"_type": "tag", "name": "__anone27382070c03", "path": "/home/kavia/workspace/code-generation/app-gateway2/dependencies/Thunder/Source/plugins/IPlugin.h", "pattern": "/^        enum { ID = RPC::ID_AUTHENTICATE };$/", "language": "C++", "kind": "enum", "scope": "WPEFramework::PluginHost::IAuthenticate", "scopeKind": "struct"}], "hash": "ebf9fb39feafe1d158a4c21783d526f7", "format-version": 4, "code-base-name": "app-gateway2", "filename": "dependencies/Thunder/Source/plugins/IPlugin.h", "revision_history": [{"4834": ""}]}