{"is_source_file": true, "format": "C++ header file", "description": "This file defines interfaces for NetworkTools JSON-RPC API, including includes for data and implementation headers.", "external_files": ["JsonData_NetworkTools.h", "JNetworkTools.h"], "external_methods": [], "published": [], "classes": [], "methods": [], "calls": [], "search-terms": ["INetworkTools", "JSON-RPC", "NetworkTools", "json_INetworkTools"], "state": 2, "file_id": 8895, "knowledge_revision": 18560, "git_revision": "a019ef1ecf9043a6387775f8d60762f619f4c761", "ctags": [], "hash": "848267f89c8570594f49eb50295d2bda", "format-version": 4, "code-base-name": "app-gateway2", "filename": "dependencies/build/ThunderInterfaces/definitions/generated/json_INetworkTools.h", "revision_history": [{"18560": "a019ef1ecf9043a6387775f8d60762f619f4c761"}]}