{"is_source_file": true, "format": "C++", "description": "This is a C++ source file (Module.cpp) associated with a module in a project, responsible for module initialization or related functionality. It includes license headers and includes a header file 'Module.h'.", "external_files": ["Module.h"], "external_methods": [], "published": [], "classes": [], "methods": [], "calls": ["MODULE_NAME_DECLARATION"], "search-terms": ["Module.cpp", "MODULE_NAME_DECLARATION", "Build_reference"], "state": 2, "file_id": 8670, "knowledge_revision": 17402, "git_revision": "", "ctags": [], "hash": "264ed26146de1667c0080333c03def18", "format-version": 4, "code-base-name": "app-gateway2", "filename": "dependencies/entservices-infra/StorageManager/Module.cpp", "revision_history": [{"17402": ""}]}