{"is_source_file": true, "format": "C++ header file", "description": "This file is a header (.h) file for a messaging module in a C++ project, setting up include guards, dependencies, and licensing information.", "external_files": ["MessageClient.h", "Logging.h", "LoggingCategories.h", "DirectOutput.h", "TraceCategories.h", "TraceControl.h", "Control.h", "TraceFactory.h", "TextMessage.h"], "external_methods": [], "published": [], "classes": [], "methods": [], "calls": [], "search-terms": ["messaging.h", "messaging", "MessageClient", "Logging", "TraceCategories"], "state": 2, "file_id": 2392, "knowledge_revision": 4967, "git_revision": "", "ctags": [], "hash": "7f3e2b66261d3081c3b26d49d327bd15", "format-version": 4, "code-base-name": "app-gateway2", "filename": "dependencies/Thunder/Source/messaging/messaging.h", "revision_history": [{"4967": ""}]}