{"is_source_file": true, "format": "CMake", "description": "This file contains CMake functions, macros, and scripts designed for build configuration. It includes functions for managing target properties, generating configuration files, handling dependencies, and install routines specific to CMake-based projects.", "external_files": ["cmake/templates/defaultConfig.cmake.in", "cmake/templates/default.pc.in", "cmake/helpers"], "external_methods": ["find_file", "message", "configure_file", "install", "get_target_property", "add_library", "list", "string", "file", "cmake_parse_arguments", "execute_process"], "published": ["add_element", "_get_default_link_name", "get_if_link_libraries", "get_if_compile_defines", "get_if_compile_options", "get_if_include_dirs", "InstallCMakeConfig", "InstallPackageConfig", "InstallFindModule", "print_properties", "print_target_properties", "semicolon_safe_string", "InstallCompatibleCMakeConfig"], "classes": [], "methods": [{"name": "add_element", "description": "Appends an element to a specified list variable."}, {"name": "_get_default_link_name", "description": "Derives a standardized link name and location from a library path."}, {"name": "get_if_link_libraries", "description": "Retrieves and processes link libraries and directories for a target, including dependencies."}, {"name": "get_if_compile_defines", "description": "Collects compile-time definitions from a target, including interface dependencies."}, {"name": "get_if_compile_options", "description": "Gathers compile options from a target and its interface dependencies."}, {"name": "get_if_include_dirs", "description": "Collects include directories from a target and its interface dependencies, resolving paths."}, {"name": "InstallCMakeConfig", "description": "Generates and installs CMake configuration files for a target, supporting versioning and dependencies."}, {"name": "InstallPackageConfig", "description": "Creates and installs pkg-config (.pc) files with options for include dirs, defines, and dependencies."}, {"name": "InstallFindModule", "description": "Installs CMake find modules (*.cmake files) from specified directories, optionally recursively."}, {"name": "print_properties", "description": "Outputs a list of CMake properties supported."}, {"name": "print_target_properties", "description": "Displays all properties of a specified target."}, {"name": "semicolon_safe_string", "description": "Replaces semicolons in a string with a placeholder to ensure string safety."}, {"name": "InstallCompatibleCMakeConfig", "description": "Creates an interface library to support legacy target compatibility with install rules and public headers."}], "calls": ["cmake_parse_arguments", "find_file", "message", "configure_file", "install", "get_target_property", "add_library", "list", "string", "file", "execute_process"], "search-terms": ["CMake functions", "CMake include", "target property", "install routines", "generate config files", "dependency handling", "pkg-config", "cmake modules", "legacy interface", "target linking"], "state": 2, "file_id": 2548, "knowledge_revision": 5130, "git_revision": "", "hash": "309501d6e05615afe0566517dc8c6853", "format-version": 4, "code-base-name": "app-gateway2", "filename": "dependencies/Thunder/cmake/common/CmakeHelperFunctions.cmake", "revision_history": [{"5130": ""}]}